[
  {
    "type": "struct",
    "name": "governance::types::PropDetails",
    "members": [
      {
        "name": "impl_hash",
        "type": "core::felt252"
      },
      {
        "name": "to_upgrade",
        "type": "core::felt252"
      }
    ]
  },
  {
    "type": "function",
    "name": "get_proposal_details",
    "inputs": [
      {
        "name": "prop_id",
        "type": "core::felt252"
      }
    ],
    "outputs": [
      {
        "type": "governance::types::PropDetails"
      }
    ],
    "state_mutability": "view"
  },
  {
    "type": "function",
    "name": "get_vote_counts",
    "inputs": [
      {
        "name": "prop_id",
        "type": "core::felt252"
      }
    ],
    "outputs": [
      {
        "type": "(core::felt252, core::felt252)"
      }
    ],
    "state_mutability": "view"
  },
  {
    "type": "function",
    "name": "submit_proposal",
    "inputs": [
      {
        "name": "impl_hash",
        "type": "core::felt252"
      },
      {
        "name": "to_upgrade",
        "type": "core::felt252"
      }
    ],
    "outputs": [
      {
        "type": "core::felt252"
      }
    ],
    "state_mutability": "external"
  },
  {
    "type": "function",
    "name": "vote",
    "inputs": [
      {
        "name": "prop_id",
        "type": "core::felt252"
      },
      {
        "name": "opinion",
        "type": "core::felt252"
      }
    ],
    "outputs": [],
    "state_mutability": "external"
  },
  {
    "type": "function",
    "name": "get_proposal_status",
    "inputs": [
      {
        "name": "prop_id",
        "type": "core::felt252"
      }
    ],
    "outputs": [
      {
        "type": "core::felt252"
      }
    ],
    "state_mutability": "view"
  },
  {
    "type": "function",
    "name": "vote_investor",
    "inputs": [
      {
        "name": "prop_id",
        "type": "core::felt252"
      },
      {
        "name": "opinion",
        "type": "core::felt252"
      }
    ],
    "outputs": [],
    "state_mutability": "external"
  },
  {
    "type": "function",
    "name": "get_governance_token_address",
    "inputs": [],
    "outputs": [
      {
        "type": "core::starknet::contract_address::ContractAddress"
      }
    ],
    "state_mutability": "view"
  },
  {
    "type": "function",
    "name": "get_amm_address",
    "inputs": [],
    "outputs": [
      {
        "type": "core::starknet::contract_address::ContractAddress"
      }
    ],
    "state_mutability": "view"
  },
  {
    "type": "function",
    "name": "apply_passed_proposal",
    "inputs": [
      {
        "name": "prop_id",
        "type": "core::felt252"
      }
    ],
    "outputs": [],
    "state_mutability": "external"
  },
  {
    "type": "function",
    "name": "claim",
    "inputs": [
      {
        "name": "address",
        "type": "core::starknet::contract_address::ContractAddress"
      },
      {
        "name": "amount",
        "type": "core::integer::u128"
      },
      {
        "name": "proof",
        "type": "core::array::Array::<core::felt252>"
      }
    ],
    "outputs": [],
    "state_mutability": "external"
  },
  {
    "type": "event",
    "name": "Proposed",
    "inputs": [
      {
        "name": "prop_id",
        "type": "core::felt252"
      },
      {
        "name": "impl_hash",
        "type": "core::felt252"
      },
      {
        "name": "to_upgrade",
        "type": "core::felt252"
      }
    ]
  },
  {
    "type": "event",
    "name": "Voted",
    "inputs": [
      {
        "name": "prop_id",
        "type": "core::felt252"
      },
      {
        "name": "voter",
        "type": "core::starknet::contract_address::ContractAddress"
      },
      {
        "name": "opinion",
        "type": "core::felt252"
      }
    ]
  },
  {
    "type": "event",
    "name": "Claimed",
    "inputs": [
      {
        "name": "address",
        "type": "core::starknet::contract_address::ContractAddress"
      },
      {
        "name": "received",
        "type": "core::integer::u128"
      }
    ]
  }
]
